legopack/__init__.py
legopack/tools.py
legopack/models/__init__.py
legopack/models/adaptators.py
legopack/models/custom.py
legopack-0.26.dist-info/METADATA
legopack-0.26.dist-info/WHEEL
legopack-0.26.dist-info/top_level.txt
legopack-0.26.dist-info/RECORD
