Metadata-Version: 2.1
Name: legopack
Version: 0.26
Summary: personal
Author: Remi Prince
Requires-Python: >=3.8
Requires-Dist: numpy
Requires-Dist: scikit-learn
Requires-Dist: streamad
